libimobiledevice/__init__.py
libimobiledevice/afc.py
libimobiledevice/device.py
libimobiledevice/libibackup.py
libimobiledevice/libirestore.py
libimobiledevice/libplist.py
libimobiledevice/service.py
libimobiledevice/util/__init__.py
libimobiledevice-0.4.dist-info/LICENSE
libimobiledevice-0.4.dist-info/WHEEL
libimobiledevice-0.4.dist-info/METADATA
libimobiledevice-0.4.dist-info/RECORD
